loggerk/__init__.py
loggerk/config/__init__.py
loggerk/formatters/__init__.py
loggerk/handlers/__init__.py
loggerk-0.0.6.dist-info/LICENSE
loggerk-0.0.6.dist-info/METADATA
loggerk-0.0.6.dist-info/WHEEL
loggerk-0.0.6.dist-info/top_level.txt
loggerk-0.0.6.dist-info/RECORD
