Metadata-Version: 2.1
Name: loggerk
Version: 0.0.6
Summary: This is a custom logger module for Python
Author: Kuantik DataJump
Author-email: master@kuantik.mx
Maintainer: Angel de Jesús Sanchez Morales
Maintainer-email: angel.sanchez@kuantik.mx
Keywords: python,logging
Classifier: Development Status :: 3 - Alpha
Classifier: Intended Audience :: Developers
Classifier: Programming Language :: Python :: 3
Classifier: Operating System :: Unix
Classifier: Operating System :: MacOS :: MacOS X
Classifier: Operating System :: Microsoft :: Windows
License-File: LICENSE
Requires-Dist: httpx
